{
    "1级材料宝箱": {
        "显示名": "§n原木宝匣",
        "星级": 2,
        "描述": "未开封的宝匣， 内含的宝藏令人遐想连篇...\n◆ §7使用以获得 §6e1 §f~ §e2 §f级原料。"
    },
    "2级材料宝箱": {
        "显示名": "§7花岗岩宝匣",
        "星级": 2,
        "描述": "未开封的宝匣， 内含的宝藏令人遐想连篇...\n◆ §7使用以获得 §e1 §f~ §e3 §f级原料。"
    },
    "3级材料宝箱": {
        "显示名": "§6黄铜宝匣",
        "星级": 3,
        "描述": "未开封的宝匣， 内含的宝藏令人遐想连篇...\n◆ §7使用以获得 §e2 §f~ §e3 §f级原料。"
    },
    "4级材料宝箱": {
        "显示名": "§7陨铁宝匣",
        "星级": 3,
        "描述": "未开封的宝匣， 内含的宝藏令人遐想连篇...\n◆ §7使用以获得 §e3 §f级原料。"
    },
    "5级材料宝箱": {
        "显示名": "§7陨铁宝匣",
        "星级": 3,
        "描述": "未开封的宝匣， 内含的宝藏令人遐想连篇...\n◆ §7使用以获得 §e3 §f级原料。"
    },
    "普通食材宝箱": {
        "显示名": "§n果木食材匣",
        "星级": 2,
        "描述": "装着各类食材的匣子， 香气隐约可闻。"
    }
}